Metadata-Version: 1.0
Name: lols0
Version: 0.5
Summary: base de datos
Home-page: https://github.com/franckp1/Finalz
Author: Andres Pérez C
Author-email: UNKNOWN
License: MIT
Platform: UNKNOWN
